notion2markdown/__init__.py
notion2markdown/cli.py
notion2markdown/json2md.py
notion2markdown/notion.py
notion2markdown/utils.py
notion2markdown-0.2.0.dist-info/LICENSE
notion2markdown-0.2.0.dist-info/METADATA
notion2markdown-0.2.0.dist-info/WHEEL
notion2markdown-0.2.0.dist-info/entry_points.txt
notion2markdown-0.2.0.dist-info/top_level.txt
notion2markdown-0.2.0.dist-info/RECORD
