Metadata-Version: 2.1
Name: notion2markdown
Version: 0.2.0
Summary: Export notion pages to markdown in Python
Author-email: Alvin Wan <hi@alvinwan.com>
Project-URL: Homepage, https://github.com/alvinwan/notion2markdown
Project-URL: Bug Tracker, https://github.com/alvinwan/notion2markdown/issues
Classifier: Programming Language :: Python :: 3
Classifier: License :: OSI Approved :: MIT License
Classifier: Operating System :: OS Independent
Requires-Python: >=3.7
License-File: LICENSE
Requires-Dist: notion-client
